AUTHORS.rst
CONTRIBUTING.rst
HISTORY.rst
LICENSE.txt
MANIFEST.in
README.rst
setup.cfg
setup.py
versioneer.py
docs/Makefile
docs/api.rst
docs/authors.rst
docs/conf.py
docs/contributing.rst
docs/history.rst
docs/index.rst
docs/installation.rst
docs/make.bat
docs/readme.rst
docs/usage.rst
tests/__init__.py
tests/test_core.py
yail/__init__.py
yail/_version.py
yail/core.py
yail.egg-info/PKG-INFO
yail.egg-info/SOURCES.txt
yail.egg-info/dependency_links.txt
yail.egg-info/not-zip-safe
yail.egg-info/requires.txt
yail.egg-info/top_level.txt